apeex/__init__.py
apeex/adapters/__init__.py
apeex/adapters/cli/__init__.py
apeex/adapters/cli/command_runner_adapter.py
apeex/adapters/config/__init__.py
apeex/adapters/config/yaml_loader_adapter.py
apeex/adapters/container/__init__.py
apeex/adapters/container/container_adapter.py
apeex/adapters/http/__init__.py
apeex/adapters/http/fastapi_response_emitter.py
apeex/adapters/http/http_kernel_adapter.py
apeex/adapters/http/request_adapter.py
apeex/adapters/http/response_adapter.py
apeex/adapters/http/router_adapter.py
apeex/adapters/orm/__init__.py
apeex/adapters/orm/base_entity_manager_adapter.py
apeex/adapters/orm/orm_adapter.py
apeex/adapters/orm/postgres_entity_manager_adapter.py
apeex/adapters/orm/sql_lite_entity_manager_adapter.py
apeex/adapters/orm/unit_of_work_adapter.py
apeex/adapters/yaml/__init__.py
apeex/adapters/yaml/yaml_loader_adapter.py
apeex/bundles/__init__.py
apeex/bundles/bundle.py
apeex/bundles/demo_bundle/__init__.py
apeex/bundles/demo_bundle/bundle.py
apeex/bundles/demo_bundle/controllers/__init__.py
apeex/bundles/demo_bundle/controllers/hello_controller.py
apeex/bundles/demo_bundle/services/__init__.py
apeex/bundles/demo_bundle/services/hello_services.py
apeex/container/__init__.py
apeex/container/container.py
apeex/container/simple_container.py
apeex/contracts/__init__.py
apeex/contracts/bundle/__init__.py
apeex/contracts/bundle/bundle_interface.py
apeex/contracts/cache/__init__.py
apeex/contracts/cache/cache_interface.py
apeex/contracts/cli/__init__.py
apeex/contracts/cli/command_runner_interface.py
apeex/contracts/config/__init__.py
apeex/contracts/config/config_loader_interface.py
apeex/contracts/container/__init__.py
apeex/contracts/container/container_interface.py
apeex/contracts/event/__init__.py
apeex/contracts/event/event_dispatcher_interface.py
apeex/contracts/http/__init__.py
apeex/contracts/http/controller_resolver_interface.py
apeex/contracts/http/http_kernel_interface.py
apeex/contracts/http/request_interface.py
apeex-0.1.0a1.dist-info/METADATA
apeex-0.1.0a1.dist-info/WHEEL
apeex-0.1.0a1.dist-info/RECORD
