Metadata-Version: 2.3
Name: apeex
Version: 0.1.0a1
Summary: A modular, interface-driven web framework inspired by Symfony, built on top of FastAPI.
License: MIT
Keywords: framework,fastapi,symfony,web,dependency-injection
Author: Apeex Team
Author-email: team@apeex.dev
Requires-Python: >=3.11
Classifier: Development Status :: 3 - Alpha
Classifier: Intended Audience :: Developers
Classifier: License :: OSI Approved :: MIT License
Classifier: Programming Language :: Python :: 3.11
Classifier: Programming Language :: Python :: 3.12
Classifier: Framework :: FastAPI
Classifier: Topic :: Software Development :: Libraries :: Application Frameworks
Requires-Dist: PyYAML (>=6.0,<7.0)
Requires-Dist: SQLAlchemy (>=2.0.22,<3.0.0)
Requires-Dist: aiosqlite (>=0.18.0,<0.19.0)
Requires-Dist: asyncpg (>=0.30.0,<0.31.0)
Requires-Dist: fastapi (>=0.115.0,<0.116.0)
Requires-Dist: uvicorn (>=0.30.0,<0.31.0)
Project-URL: Documentation, https://github.com/dvakhitov/apeex-framework
Project-URL: Homepage, https://github.com/dvakhitov/apeex-framework
Project-URL: Source, https://github.com/dvakhitov/apeex-framework
